session/__init__.py
session/session_context.py
comapsmarthome_orm_utils-0.1.2.dist-info/LICENSE
comapsmarthome_orm_utils-0.1.2.dist-info/METADATA
comapsmarthome_orm_utils-0.1.2.dist-info/WHEEL
comapsmarthome_orm_utils-0.1.2.dist-info/top_level.txt
comapsmarthome_orm_utils-0.1.2.dist-info/RECORD
