Metadata-Version: 2.1
Name: comapsmarthome-orm-utils
Version: 0.1.2
Summary: ORM stuff for ComapSmartHome
Home-page: UNKNOWN
Author: Aurélien Sylvan
Author-email: aurelien.sylvan@comap.eu
License: UNKNOWN
Platform: UNKNOWN
Classifier: Programming Language :: Python :: 3
Classifier: License :: OSI Approved :: MIT License
Classifier: Operating System :: OS Independent
Requires-Dist: psycopg2-binary (>=2.8.0)
